{"propertiesBar":{"properties":[{"name":"About","expanded":true,"children":[]},{"name":"Colors","expanded":true,"children":[]},{"name":"Startup","expanded":true,"children":[]},{"name":"Display","expanded":true,"children":[{"name":"Viewport size","expanded":false,"children":[]}]},{"name":"Advanced","expanded":true,"children":[]},{"name":"Compatibility settings","expanded":true,"children":[]},{"name":"Editor","expanded":true,"children":[]}],"scrollPosition":0},"openTabs":{"active":{"name":"Event sheet 1","type":"eventSheet"},"open":[{"name":"Layout 1","type":"layout"},{"name":"Event sheet 1","type":"eventSheet"}]},"previewEffects":true,"previewBrowser":"nwjs","pauseOnUnfocus":false,"projectBar":{"name":"<root>","children":[{"name":"IWANT","expanded":true,"children":[{"name":"Layouts","expanded":true,"children":[{"name":"Layout 1","expanded":true,"children":[]}]},{"name":"Event sheets","expanded":true,"children":[{"name":"Event sheet 1","expanded":true,"children":[]}]},{"name":"Scripts","expanded":true,"children":[]},{"name":"Object types","expanded":true,"children":[{"name":"9P_DialogBack","expanded":true,"children":[]},{"name":"9P_Inventory","expanded":true,"children":[]},{"name":"A_Destroyer","expanded":true,"children":[]},{"name":"A_FinalPhrase","expanded":true,"children":[]},{"name":"A_Inventory","expanded":true,"children":[]},{"name":"A_Level","expanded":true,"children":[]},{"name":"A_Map","expanded":true,"children":[]},{"name":"A_QueryActions","expanded":true,"children":[]},{"name":"Function","expanded":true,"children":[]},{"name":"Hero","expanded":true,"children":[]},{"name":"Idea","expanded":true,"children":[]},{"name":"Item","expanded":true,"children":[]},{"name":"Keyboard","expanded":true,"children":[]},{"name":"Magic","expanded":true,"children":[]},{"name":"Mouse","expanded":true,"children":[]},{"name":"NPC","expanded":true,"children":[]},{"name":"OverlappingIdeas","expanded":true,"children":[]},{"name":"SF_DAMAGE","expanded":true,"children":[]},{"name":"SF_DEBUG","expanded":true,"children":[]},{"name":"SF_GOLD","expanded":true,"children":[]},{"name":"SF_HP","expanded":true,"children":[]},{"name":"SF_IdeaName","expanded":true,"children":[]},{"name":"SF_InteractSummury","expanded":true,"children":[]},{"name":"SF_LVL","expanded":true,"children":[]},{"name":"SF_SpeechText","expanded":true,"children":[]},{"name":"SF_StaticText","expanded":true,"children":[]},{"name":"SF_Title","expanded":true,"children":[]},{"name":"T_DEAD","expanded":true,"children":[]},{"name":"T_Grid","expanded":true,"children":[]},{"name":"T_HUD","expanded":true,"children":[]},{"name":"TM_LevelGround","expanded":true,"children":[]},{"name":"TM_LevelWall","expanded":true,"children":[]},{"name":"Touch","expanded":true,"children":[]}]},{"name":"Families","expanded":true,"children":[{"name":"Ideas","expanded":false,"children":[{"name":"Idea","expanded":true,"children":[]}]},{"name":"Sort","expanded":false,"children":[{"name":"Hero","expanded":true,"children":[]},{"name":"Item","expanded":true,"children":[]},{"name":"NPC","expanded":true,"children":[]}]}]},{"name":"Timelines","expanded":true,"children":[{"name":"Eases","expanded":false,"children":[]}]},{"name":"Flowcharts","expanded":true,"children":[]},{"name":"Sounds","expanded":true,"children":[]},{"name":"Music","expanded":true,"children":[]},{"name":"Videos","expanded":true,"children":[]},{"name":"Fonts","expanded":true,"children":[]},{"name":"Icons & screenshots","expanded":false,"children":[{"name":"icon-114.png","expanded":true,"children":[]},{"name":"icon-128.png","expanded":true,"children":[]},{"name":"icon-16.png","expanded":true,"children":[]},{"name":"icon-256.png","expanded":true,"children":[]},{"name":"icon-32.png","expanded":true,"children":[]},{"name":"loading-logo.png","expanded":true,"children":[]}]},{"name":"Files","expanded":true,"children":[]}]}]},"propertiesBarActiveObject":{"name":"instances","type":"array"},"containers":[{"selectMode":"normal"}]}